ghidralib.py
ghidralib-0.2.0.dist-info/METADATA
ghidralib-0.2.0.dist-info/WHEEL
ghidralib-0.2.0.dist-info/top_level.txt
ghidralib-0.2.0.dist-info/RECORD
