Metadata-Version: 2.4
Name: ghidralib
Version: 0.2.0
Summary:  A Pythonic Ghidra standard library
Author-email: msm <msm@tailcall.net>
License-Expression: MIT
Project-URL: Homepage, https://github.com/msm-code/ghidralib
Project-URL: Issues, https://github.com/msm-code/ghidralib/issues
Classifier: Programming Language :: Python :: 3
Classifier: Operating System :: OS Independent
Requires-Python: >=3.8
